pkrhistoryconverter/__init__.py
pkrhistoryconverter/converter.py
pkrhistoryconverter/utils/__init__.py
pkrhistoryconverter/utils/exceptions.py
pkrhistoryconverter-1.3.11.dist-info/LICENSE.txt
pkrhistoryconverter-1.3.11.dist-info/METADATA
pkrhistoryconverter-1.3.11.dist-info/WHEEL
pkrhistoryconverter-1.3.11.dist-info/top_level.txt
pkrhistoryconverter-1.3.11.dist-info/RECORD
